<?xml version="1.0" encoding="utf-8" ?><?pageview_candidate?><SearchSuggestion xmlns="http://schemas.microsoft.com/Search/2008/suggestions"><Query>yahoo</Query><Section><Item><Text>yahoo</Text></Item><Item><Text>yahoo.com</Text></Item><Item><Text>yahoo mail</Text></Item><Item><Text>yahoo mail login</Text></Item><Item><Text>yahoo.com login</Text></Item><Item><Text>yahoo finance</Text></Item><Item><Text>yahoo mail sign in</Text></Item><Item><Text>yahoo news</Text></Item><Item><Text>yahoo sports</Text></Item><Item><Text>yahoo mail log in</Text></Item><Item><Text>yahoo.com mail</Text></Item><Item><Text>yahoo email</Text></Item><Item><Text>yahoo fantasy football</Text></Item><Item><Text>yahoo.mail</Text></Item><Item><Text>yahoo maps</Text></Item><Item><Text>yahoo games</Text></Item><Item><Text>yahoo japan</Text></Item><Item><Text>yahoo.com sign in</Text></Item><Item><Text>yahoo messenger</Text></Item><Item><Text>yahoomailsign.in</Text></Item><Item><Text>yahoo sign in</Text></Item><Item><Text>yahoo answers</Text></Item><Item><Text>yahoo.com mail login</Text></Item><Item><Text>yahoo mail inbox</Text></Item><Item><Text>yahoo homepage</Text></Item></Section></SearchSuggestion>